canvasgrader/__init__.py
canvasgrader-1.0.2.dist-info/DESCRIPTION.rst
canvasgrader-1.0.2.dist-info/METADATA
canvasgrader-1.0.2.dist-info/RECORD
canvasgrader-1.0.2.dist-info/WHEEL
canvasgrader-1.0.2.dist-info/metadata.json
canvasgrader-1.0.2.dist-info/top_level.txt
