Metadata-Version: 2.0
Name: canvasgrader
Version: 1.0.2
Summary: Simple grading interface with the Canvas API
Home-page: https://github.com/mterwill/canvasgrader
Author: Matthew Terwilliger
Author-email: matt+canvasgrader@terwilligers.com
License: MIT
Keywords: canvas learning management system lms grade grades grading
Platform: UNKNOWN
Classifier: Development Status :: 4 - Beta
Classifier: Intended Audience :: Developers
Classifier: Intended Audience :: Education
Classifier: Topic :: Education
Classifier: License :: OSI Approved :: MIT License
Classifier: Programming Language :: Python :: 2
Classifier: Programming Language :: Python :: 2.6
Classifier: Programming Language :: Python :: 2.7
Classifier: Programming Language :: Python :: 3
Classifier: Programming Language :: Python :: 3.3
Classifier: Programming Language :: Python :: 3.4
Classifier: Programming Language :: Python :: 3.5
Requires-Dist: requests
